gifs/.gitattributes
gifs/ui.png
gifs/xpc_print_message.gif
hilda/__init__.py
hilda/__main__.py
hilda/_version.py
hilda/breakpoints.py
hilda/cli.py
hilda/common.py
hilda/decorators.py
hilda/exceptions.py
hilda/hilda_client.py
hilda/launch_lldb.py
hilda/lldb_entrypoint.py
hilda/lldb_importer.py
hilda/objective_c_class.py
hilda/objective_c_symbol.py
hilda/registers.py
hilda/symbol.py
hilda/symbols.py
hilda/watchpoints.py
hilda/ipython_extensions/events.py
hilda/ipython_extensions/keybindings.py
hilda/ipython_extensions/magics.py
hilda/objective_c/from_ns_to_json.m
hilda/objective_c/get_objectivec_class_by_module.m
hilda/objective_c/get_objectivec_class_description.m
hilda/objective_c/get_objectivec_symbol_data.m
hilda/objective_c/lsof.m
hilda/objective_c/to_ns_from_json.m
hilda/snippets/__init__.py
hilda/snippets/boringssl.py
hilda/snippets/collections.py
hilda/snippets/dyld.py
hilda/snippets/fs_utils.py
hilda/snippets/libmalloc.py
hilda/snippets/remotepairingd.py
hilda/snippets/syslog.py
hilda/snippets/uuid.py
hilda/snippets/xpc.py
hilda/snippets/mach/CFRunLoopServiceMachPort_hooks.py
hilda/snippets/mach/__init__.py
hilda/snippets/macho/__init__.py
hilda/snippets/macho/all_image_infos.py
hilda/snippets/macho/apple_version.py
hilda/snippets/macho/image_info.py
hilda/snippets/macho/macho.py
hilda/snippets/macho/macho_load_commands.py
hilda/ui/colors.json
hilda/ui/ui_manager.py
hilda/ui/views.py
hilda-3.4.3.dist-info/licenses/LICENSE
hilda-3.4.3.dist-info/METADATA
hilda-3.4.3.dist-info/WHEEL
hilda-3.4.3.dist-info/entry_points.txt
hilda-3.4.3.dist-info/top_level.txt
hilda-3.4.3.dist-info/RECORD
