Metadata-Version: 2.4
Name: hilda
Version: 3.4.3
Summary: LLDB wrapped and empowered by iPython's features
Author-email: doronz88 <doron88@gmail.com>, matan <matan1008@gmail.com>, netanel cohen <netanelc305@protonmail.com>
Maintainer-email: doronz88 <doron88@gmail.com>, matan <matan1008@gmail.com>, netanel cohen <netanelc305@protonmail.com>
License: Copyright (c) 2012-2023 Doron Zarhi and Metan Perelman
Project-URL: Homepage, https://github.com/doronz88/hilda
Project-URL: Bug Reports, https://github.com/doronz88/hilda/issues
Keywords: python,debugger,lldb,ipython,ios,debug
Classifier: Operating System :: MacOS
Classifier: Development Status :: 5 - Production/Stable
Classifier: License :: OSI Approved :: MIT License
Classifier: Programming Language :: Python :: 3
Classifier: Programming Language :: Python :: 3.9
Classifier: Programming Language :: Python :: 3.10
Classifier: Programming Language :: Python :: 3.11
Classifier: Programming Language :: Python :: 3.12
Classifier: Programming Language :: Python :: 3.13
Classifier: Programming Language :: Python :: 3 :: Only
Requires-Python: >=3.9
License-File: LICENSE
Requires-Dist: tqdm
Requires-Dist: docstring_parser
Requires-Dist: coloredlogs
Requires-Dist: hexdump
Requires-Dist: ipython
Requires-Dist: click
Requires-Dist: objc_types_decoder
Requires-Dist: construct
Requires-Dist: pymobiledevice3
Requires-Dist: keystone-engine
Requires-Dist: tabulate
Requires-Dist: inquirer3
Requires-Dist: traitlets
Provides-Extra: test
Requires-Dist: pytest; extra == "test"
Dynamic: license-file
